twitter_openapi_python_generated/__init__.py
twitter_openapi_python_generated/api_client.py
twitter_openapi_python_generated/api_response.py
twitter_openapi_python_generated/configuration.py
twitter_openapi_python_generated/exceptions.py
twitter_openapi_python_generated/py.typed
twitter_openapi_python_generated/rest.py
twitter_openapi_python_generated/api/__init__.py
twitter_openapi_python_generated/api/default_api.py
twitter_openapi_python_generated/api/other_api.py
twitter_openapi_python_generated/api/post_api.py
twitter_openapi_python_generated/api/tweet_api.py
twitter_openapi_python_generated/api/user_api.py
twitter_openapi_python_generated/api/user_list_api.py
twitter_openapi_python_generated/api/users_api.py
twitter_openapi_python_generated/api/v11_get_api.py
twitter_openapi_python_generated/api/v11_post_api.py
twitter_openapi_python_generated/api/v20_get_api.py
twitter_openapi_python_generated/models/__init__.py
twitter_openapi_python_generated/models/about_community_result.py
twitter_openapi_python_generated/models/about_community_results.py
twitter_openapi_python_generated/models/about_community_tweet_data.py
twitter_openapi_python_generated/models/additional_media_info.py
twitter_openapi_python_generated/models/additional_media_info_call_to_actions.py
twitter_openapi_python_generated/models/additional_media_info_call_to_actions_url.py
twitter_openapi_python_generated/models/allow_download_status.py
twitter_openapi_python_generated/models/analysis_results.py
twitter_openapi_python_generated/models/article.py
twitter_openapi_python_generated/models/article_cover_media.py
twitter_openapi_python_generated/models/article_cover_media_color_info.py
twitter_openapi_python_generated/models/article_cover_media_color_info_palette.py
twitter_openapi_python_generated/models/article_cover_media_color_info_palette_rgb.py
twitter_openapi_python_generated/models/article_cover_media_info.py
twitter_openapi_python_generated/models/article_lifecycle_state.py
twitter_openapi_python_generated-0.0.33.dist-info/licenses/LICENSE
twitter_openapi_python_generated-0.0.33.dist-info/licenses/LICENSE.AGPL
twitter_openapi_python_generated-0.0.33.dist-info/METADATA
twitter_openapi_python_generated-0.0.33.dist-info/WHEEL
twitter_openapi_python_generated-0.0.33.dist-info/top_level.txt
twitter_openapi_python_generated-0.0.33.dist-info/RECORD
