Metadata-Version: 2.4
Name: twitter_openapi_python_generated
Version: 0.0.33
Summary: Twitter OpenAPI
Home-page: https://github.com/fa0311/twitter_openapi_python_generated
Author: OpenAPI Generator community
Author-email: yuki@yuki0311.com
License: custom license or AGPL-3.0-or-later
Keywords: OpenAPI,OpenAPI-Generator,Twitter OpenAPI
License-File: LICENSE
License-File: LICENSE.AGPL
Requires-Dist: urllib3<3.0.0,>=1.25.3
Requires-Dist: python-dateutil>=2.8.2
Requires-Dist: pydantic>=2
Requires-Dist: typing-extensions>=4.7.1
Dynamic: author
Dynamic: author-email
Dynamic: description
Dynamic: description-content-type
Dynamic: home-page
Dynamic: keywords
Dynamic: license
Dynamic: license-file
Dynamic: requires-dist
Dynamic: summary
